README.md
setup.cfg
setup.py
sms/__init__.py
sms/echo.py
sms/encoding.py
sms/server.py
sms/tests.py
sms/unaccent.py
sms3/__init__.py
sms3.egg-info/PKG-INFO
sms3.egg-info/SOURCES.txt
sms3.egg-info/dependency_links.txt
sms3.egg-info/requires.txt
sms3.egg-info/top_level.txt