Metadata-Version: 1.1
Name: sms3
Version: 0.0.2
Summary: A library for sending TXT message
Home-page: https://github.com/yanganto/sms3
Author: yanganto
Author-email: yanganto@gmail.com
License: MIT
Keywords: sms
Platform: UNKNOWN
Classifier: Programming Language :: Python
Classifier: Programming Language :: Python :: 3.5
Classifier: Programming Language :: Python :: 3 :: Only
Classifier: Topic :: Communications :: Telephony
